interactions/ext/enhanced/__init__.py
interactions/ext/enhanced/_logging.py
interactions/ext/enhanced/alt_ext.py
interactions/ext/enhanced/callbacks.py
interactions/ext/enhanced/command_models.py
interactions/ext/enhanced/commands.py
interactions/ext/enhanced/components.py
interactions/ext/enhanced/cooldowns.py
interactions/ext/enhanced/extension.py
enhanced-4.0.1.dist-info/LICENSE
enhanced-4.0.1.dist-info/METADATA
enhanced-4.0.1.dist-info/WHEEL
enhanced-4.0.1.dist-info/top_level.txt
enhanced-4.0.1.dist-info/RECORD
