Metadata-Version: 2.1
Name: enhanced
Version: 4.0.1
Summary: Enhanced interactions for interactions.py
Home-page: https://github.com/interactions-py/enhanced
Author: Toricane
Author-email: prjwl028@gmail.com
License: MIT
Classifier: Programming Language :: Python :: 3
Classifier: Development Status :: 4 - Beta
Classifier: License :: OSI Approved :: MIT License
Classifier: Operating System :: OS Independent
License-File: LICENSE
Requires-Dist: discord-py-interactions (>=4.3.0)
Requires-Dist: typing-extensions
